tecton_client/__about__.py
tecton_client/__init__.py
tecton_client/exceptions.py
tecton_client/py.typed
tecton_client/_internal/__init__.py
tecton_client/_internal/async_tecton_client.py
tecton_client/_internal/request_utils.py
tecton_client/_internal/response_utils.py
tecton_client/_internal/tecton_client.py
tecton_client/_internal/utils.py
tecton_client-0.4.0.dist-info/METADATA
tecton_client-0.4.0.dist-info/WHEEL
tecton_client-0.4.0.dist-info/licenses/LICENSE.md
tecton_client-0.4.0.dist-info/RECORD
