Metadata-Version: 2.4
Name: tecton-client
Version: 0.4.0
Summary: A Python Client for the Tecton FeatureService API
Project-URL: Source, https://github.com/tecton-ai/tecton-http-client-python
Project-URL: Documentation, https://tecton-ai.github.io/tecton-http-client-python/html/index.html
License-Expression: Apache-2.0
License-File: LICENSE.md
Requires-Python: >=3.8
Requires-Dist: httpx>=0.23.0
Provides-Extra: dev
Requires-Dist: pytest-asyncio; extra == 'dev'
Requires-Dist: pytest-httpx; extra == 'dev'
Requires-Dist: pytest>=6.2.5; extra == 'dev'
Provides-Extra: docs
Requires-Dist: alabaster==0.7.16; extra == 'docs'
Requires-Dist: babel==2.14.0; extra == 'docs'
Requires-Dist: certifi==2024.2.2; extra == 'docs'
Requires-Dist: charset-normalizer==3.3.2; extra == 'docs'
Requires-Dist: docutils==0.20.1; extra == 'docs'
Requires-Dist: idna==3.7; extra == 'docs'
Requires-Dist: imagesize==1.4.1; extra == 'docs'
Requires-Dist: importlib-metadata==7.1.0; extra == 'docs'
Requires-Dist: jinja2==3.1.3; extra == 'docs'
Requires-Dist: markupsafe==2.1.5; extra == 'docs'
Requires-Dist: pygments==2.17.2; extra == 'docs'
Requires-Dist: snowballstemmer==2.2.0; extra == 'docs'
Requires-Dist: sphinx-rtd-theme==2.0.0; extra == 'docs'
Requires-Dist: sphinx==7.2.6; extra == 'docs'
Requires-Dist: sphinxcontrib-applehelp==1.0.8; extra == 'docs'
Requires-Dist: sphinxcontrib-devhelp==1.0.6; extra == 'docs'
Requires-Dist: sphinxcontrib-htmlhelp==2.0.5; extra == 'docs'
Requires-Dist: sphinxcontrib-jquery==4.1; extra == 'docs'
Requires-Dist: sphinxcontrib-jsmath==1.0.1; extra == 'docs'
Requires-Dist: sphinxcontrib-qthelp==1.0.7; extra == 'docs'
Requires-Dist: sphinxcontrib-serializinghtml==1.1.10; extra == 'docs'
